passive_auto_design/__init__.py
passive_auto_design/components/__init__.py
passive_auto_design/components/lumped_element.py
passive_auto_design/components/mos.py
passive_auto_design/components/transformer.py
passive_auto_design/components/waveguide.py
passive_auto_design/devices/__init__.py
passive_auto_design/devices/balun.py
passive_auto_design/devices/coupler.py
passive_auto_design/devices/taper.py
passive_auto_design/space_mapping.py
passive_auto_design/special.py
passive_auto_design/substrate.py
passive_auto_design/system/__init__.py
passive_auto_design/system/pll.py
passive_auto_design/system/rf_line_up.py
passive_auto_design/units/__init__.py
passive_auto_design/units/constants.py
passive_auto_design/units/converters.py
passive_auto_design/units/noise.py
passive_auto_design/units/physical_dimension.py
passive_auto_design/units/time.py
passive_auto_design/units/unit.py
passive_auto_design-0.1.12.dist-info/LICENSE
passive_auto_design-0.1.12.dist-info/WHEEL
passive_auto_design-0.1.12.dist-info/METADATA
passive_auto_design-0.1.12.dist-info/RECORD
